README.rst
setup.cfg
setup.py
EarthReader_Web.egg-info/PKG-INFO
EarthReader_Web.egg-info/SOURCES.txt
EarthReader_Web.egg-info/dependency_links.txt
EarthReader_Web.egg-info/entry_points.txt
EarthReader_Web.egg-info/pbr.json
EarthReader_Web.egg-info/requires.txt
EarthReader_Web.egg-info/top_level.txt
earthreader/__init__.py
earthreader/web/__init__.py
earthreader/web/command.py
earthreader/web/exceptions.py
earthreader/web/osx.py
earthreader/web/stage.py
earthreader/web/util.py
earthreader/web/worker.py
earthreader/web/wsgi.py
earthreader/web/static/css/README
earthreader/web/static/css/animation.scss.css
earthreader/web/static/css/master.scss.css
earthreader/web/static/css/theme_bright.scss.css
earthreader/web/static/css/theme_dark.scss.css
earthreader/web/static/img/favicon_32.ico
earthreader/web/static/js/master.js
earthreader/web/static/js/moment-with-langs.min.js
earthreader/web/static/js/prefixfree.min.js
earthreader/web/static/scss/animation.scss
earthreader/web/static/scss/master.scss
earthreader/web/static/scss/theme_bright.scss
earthreader/web/static/scss/theme_dark.scss
earthreader/web/templates/index.html